truerandom/__init__.py
truerandom/__main__.py
truerandom/conftest.py
truerandom/truerandom.py
truerandom/utils.py
true_random-1.2.0.dist-info/LICENSE
true_random-1.2.0.dist-info/METADATA
true_random-1.2.0.dist-info/WHEEL
true_random-1.2.0.dist-info/top_level.txt
true_random-1.2.0.dist-info/RECORD
