Metadata-Version: 2.1
Name: true-random
Version: 1.2.0
Summary: A quantum alternative for standard Python random package
Home-page: https://github.com/peb-8/true-random
Author: Pierre-Emmanuel Brian
Author-email: peb8@outlook.fr
License: UNKNOWN
Project-URL: Bug Tracker, https://github.com/peb-8/true-random/issues
Platform: UNKNOWN
Classifier: Programming Language :: Python :: 3
Classifier: License :: OSI Approved :: MIT License
Classifier: Operating System :: OS Independent
Requires-Python: >=3.6
License-File: LICENSE
Requires-Dist: quantumrandom (==1.9.0)
